glossarpy/ __init__.py
glossarpy/GlossEntry.py
glossarpy/GlossTxt.py
glossarpy/GreatGloss.py
glossarpy-0.1.2.dist-info/LICENSE
glossarpy-0.1.2.dist-info/METADATA
glossarpy-0.1.2.dist-info/WHEEL
glossarpy-0.1.2.dist-info/top_level.txt
glossarpy-0.1.2.dist-info/RECORD
