Metadata-Version: 2.1
Name: glossarpy
Version: 0.1.2
Summary: Create RST and plaintext glossaries easily
Home-page: https://github.com/aofarrel/glossarpy.git
Author: Ash O'Farrrell
Author-email: aofarrel@ucsc.edu
License: Apache 2.0
Platform: MacOS X
Platform: Posix
Classifier: Programming Language :: Python :: 3.7
Classifier: Topic :: Software Development :: Documentation
Classifier: Topic :: Text Processing :: Markup :: reStructuredText
License-File: LICENSE
